
{
    "gpt2_base_en": {
        "status": "\u2705 COMPLETED",
        "history": [
            {
                "epoch": 1,
                "loss": 4.101449489593506,
                "perplexity": 60.42781448364258,
                "sparse_categorical_accuracy": 0.28902342915534973,
                "val_loss": 3.911963701248169,
                "val_perplexity": 49.997032165527344,
                "val_sparse_categorical_accuracy": 0.298828125
            },
            {
                "epoch": 2,
                "loss": 3.8896710872650146,
                "perplexity": 48.89480209350586,
                "sparse_categorical_accuracy": 0.3138671815395355,
                "val_loss": 3.924903154373169,
                "val_perplexity": 50.64817428588867,
                "val_sparse_categorical_accuracy": 0.30351561307907104
            },
            {
                "epoch": 3,
                "loss": 3.9197144508361816,
                "perplexity": 50.38605499267578,
                "sparse_categorical_accuracy": 0.3092968761920929,
                "val_loss": 3.792914867401123,
                "val_perplexity": 44.385589599609375,
                "val_sparse_categorical_accuracy": 0.32304686307907104
            },
            {
                "epoch": 4,
                "loss": 3.7574868202209473,
                "perplexity": 42.84062194824219,
                "sparse_categorical_accuracy": 0.3258007764816284,
                "val_loss": 3.906787157058716,
                "val_perplexity": 49.738895416259766,
                "val_sparse_categorical_accuracy": 0.31474608182907104
            },
            {
                "epoch": 5,
                "loss": 4.0711283683776855,
                "perplexity": 58.623069763183594,
                "sparse_categorical_accuracy": 0.28160154819488525,
                "val_loss": 3.6575019359588623,
                "val_perplexity": 38.76438522338867,
                "val_sparse_categorical_accuracy": 0.3404296934604645
            },
            {
                "epoch": 6,
                "loss": 3.661362886428833,
                "perplexity": 38.91434097290039,
                "sparse_categorical_accuracy": 0.3367968797683716,
                "val_loss": 3.6102492809295654,
                "val_perplexity": 36.97526931762695,
                "val_sparse_categorical_accuracy": 0.34882813692092896
            },
            {
                "epoch": 7,
                "loss": 3.519054651260376,
                "perplexity": 33.752506256103516,
                "sparse_categorical_accuracy": 0.35185545682907104,
                "val_loss": 3.7072806358337402,
                "val_perplexity": 40.74285888671875,
                "val_sparse_categorical_accuracy": 0.34208983182907104
            },
            {
                "epoch": 8,
                "loss": 3.675272226333618,
                "perplexity": 39.45939636230469,
                "sparse_categorical_accuracy": 0.3355664014816284,
                "val_loss": 3.6507697105407715,
                "val_perplexity": 38.50429153442383,
                "val_sparse_categorical_accuracy": 0.34882813692092896
            },
            {
                "epoch": 9,
                "loss": 3.564418077468872,
                "perplexity": 35.31889343261719,
                "sparse_categorical_accuracy": 0.34541016817092896,
                "val_loss": 3.724820613861084,
                "val_perplexity": 41.46379470825195,
                "val_sparse_categorical_accuracy": 0.34208983182907104
            },
            {
                "epoch": 10,
                "loss": 3.8068201541900635,
                "perplexity": 45.00709533691406,
                "sparse_categorical_accuracy": 0.31392577290534973,
                "val_loss": 3.5986480712890625,
                "val_perplexity": 36.548789978027344,
                "val_sparse_categorical_accuracy": 0.3516601622104645
            }
        ]
    },
    "bloom_560m_multi": {
        "status": "\u2705 COMPLETED",
        "history": [
            {
                "epoch": 1,
                "loss": 3.8621,
                "perplexity": 47.5660,
                "sparse_categorical_accuracy": 0.3333,
                "val_loss": 4.1942,
                "val_perplexity": 66.3008,
                "val_sparse_categorical_accuracy": 0.3002
            },
            {
                "epoch": 2,
                "loss": 3.6666,
                "perplexity": 39.1190,
                "sparse_categorical_accuracy": 0.3616,
                "val_loss": 4.2178,
                "val_perplexity": 67.8829,
                "val_sparse_categorical_accuracy": 0.2999
            },
            {
                "epoch": 3,
                "loss": 3.7020,
                "perplexity": 40.5299,
                "sparse_categorical_accuracy": 0.3519,
                "val_loss": 4.0637,
                "val_perplexity": 58.1913,
                "val_sparse_categorical_accuracy": 0.3254
            },
            {
                "epoch": 4,
                "loss": 3.5060,
                "perplexity": 33.3159,
                "sparse_categorical_accuracy": 0.3661,
                "val_loss": 4.1827,
                "val_perplexity": 65.5393,
                "val_sparse_categorical_accuracy": 0.3078
            },
            {
                "epoch": 5,
                "loss": 3.8855,
                "perplexity": 48.6914,
                "sparse_categorical_accuracy": 0.3200,
                "val_loss": 3.6900,
                "val_perplexity": 40.0445,
                "val_sparse_categorical_accuracy": 0.3494
            },
            {
                "epoch": 6,
                "loss": 3.1385,
                "perplexity": 23.0701,
                "sparse_categorical_accuracy": 0.4044,
                "val_loss": 3.6579,
                "val_perplexity": 38.7794,
                "val_sparse_categorical_accuracy": 0.3536
            },
            {
                "epoch": 7,
                "loss": 2.7711,
                "perplexity": 15.9761,
                "sparse_categorical_accuracy": 0.4483,
                "val_loss": 3.8359,
                "val_perplexity": 46.3359,
                "val_sparse_categorical_accuracy": 0.3304
            },
            {
                "epoch": 8,
                "loss": 2.8512,
                "perplexity": 17.3081,
                "sparse_categorical_accuracy": 0.4347,
                "val_loss": 3.7742,
                "val_perplexity": 43.5623,
                "val_sparse_categorical_accuracy": 0.3475
            },
            {
                "epoch": 9,
                "loss": 2.7242,
                "perplexity": 15.2438,
                "sparse_categorical_accuracy": 0.4465,
                "val_loss": 3.9569,
                "val_perplexity": 52.2970,
                "val_sparse_categorical_accuracy": 0.3309
            },
            {
                "epoch": 10,
                "loss": 2.9317,
                "perplexity": 18.7597,
                "sparse_categorical_accuracy": 0.4220,
                "val_loss": 3.7056,
                "val_perplexity": 40.6729,
                "val_sparse_categorical_accuracy": 0.3486
            }
        ]
    },
    "opt_125m_en": {
        "status": "\u2705 COMPLETED",
        "history": [
            {
                "epoch": 1,
                "loss": 3.9272301197052,
                "perplexity": 50.76616668701172,
                "sparse_categorical_accuracy": 0.31611329317092896,
                "val_loss": 3.9270095825195312,
                "val_perplexity": 50.75497055053711,
                "val_sparse_categorical_accuracy": 0.3045898377895355
            },
            {
                "epoch": 2,
                "loss": 3.789726972579956,
                "perplexity": 44.24431610107422,
                "sparse_categorical_accuracy": 0.3321289122104645,
                "val_loss": 3.9531874656677246,
                "val_perplexity": 52.10116958618164,
                "val_sparse_categorical_accuracy": 0.3095703125
            },
            {
                "epoch": 3,
                "loss": 3.811566114425659,
                "perplexity": 45.2212028503418,
                "sparse_categorical_accuracy": 0.3277343809604645,
                "val_loss": 3.822160005569458,
                "val_perplexity": 45.702823638916016,
                "val_sparse_categorical_accuracy": 0.3177734315395355
            },
            {
                "epoch": 4,
                "loss": 3.673215866088867,
                "perplexity": 39.37833786010742,
                "sparse_categorical_accuracy": 0.34003907442092896,
                "val_loss": 3.958253860473633,
                "val_perplexity": 52.365806579589844,
                "val_sparse_categorical_accuracy": 0.3023437559604645
            },
            {
                "epoch": 5,
                "loss": 3.9495673179626465,
                "perplexity": 51.91290283203125,
                "sparse_categorical_accuracy": 0.3000781238079071,
                "val_loss": 3.6240952014923096,
                "val_perplexity": 37.49078369140625,
                "val_sparse_categorical_accuracy": 0.34814453125
            },
            {
                "epoch": 6,
                "loss": 3.4611666202545166,
                "perplexity": 31.854114532470703,
                "sparse_categorical_accuracy": 0.3678906261920929,
                "val_loss": 3.561530351638794,
                "val_perplexity": 35.21704864501953,
                "val_sparse_categorical_accuracy": 0.35888671875
            },
            {
                "epoch": 7,
                "loss": 3.3113198280334473,
                "perplexity": 27.421293258666992,
                "sparse_categorical_accuracy": 0.38333985209465027,
                "val_loss": 3.692692995071411,
                "val_perplexity": 40.15283203125,
                "val_sparse_categorical_accuracy": 0.34160155057907104
            },
            {
                "epoch": 8,
                "loss": 3.452059030532837,
                "perplexity": 31.565319061279297,
                "sparse_categorical_accuracy": 0.36625000834465027,
                "val_loss": 3.616868495941162,
                "val_perplexity": 37.220829010009766,
                "val_sparse_categorical_accuracy": 0.35712891817092896
            },
            {
                "epoch": 9,
                "loss": 3.353196620941162,
                "perplexity": 28.593992233276367,
                "sparse_categorical_accuracy": 0.3737109303474426,
                "val_loss": 3.732461452484131,
                "val_perplexity": 41.78182601928711,
                "val_sparse_categorical_accuracy": 0.3475585877895355
            },
            {
                "epoch": 10,
                "loss": 3.5690925121307373,
                "perplexity": 35.484375,
                "sparse_categorical_accuracy": 0.34714844822883606,
                "val_loss": 3.566401958465576,
                "val_perplexity": 35.389034271240234,
                "val_sparse_categorical_accuracy": 0.3594726622104645
            }
        ]
    }
}